find_vowels/__init__.py
find_vowels/string_tools.py
find_vowels-0.1.4.dist-info/METADATA
find_vowels-0.1.4.dist-info/WHEEL
find_vowels-0.1.4.dist-info/top_level.txt
find_vowels-0.1.4.dist-info/RECORD
