Metadata-Version: 2.4
Name: find_vowels
Version: 0.1.4
Summary: A simple custom utility library for vowels check
Author-email: Saquib & Ansh <mohdsaquib91377@gmail.com>
License: MIT
Requires-Python: >=3.7
